package com.flurry.android;

import java.util.HashMap;
import java.util.List;
import java.util.Map;

final class aa {
  private Map a = new HashMap<Object, Object>();
  
  final AdUnit a(String paramString) {
    // Byte code:
    //   0: aload_0
    //   1: monitorenter
    //   2: aload_0
    //   3: getfield a : Ljava/util/Map;
    //   6: aload_1
    //   7: invokeinterface get : (Ljava/lang/Object;)Ljava/lang/Object;
    //   12: checkcast java/util/List
    //   15: astore_1
    //   16: aload_1
    //   17: ifnull -> 86
    //   20: aload_1
    //   21: invokeinterface iterator : ()Ljava/util/Iterator;
    //   26: astore_2
    //   27: aload_2
    //   28: invokeinterface hasNext : ()Z
    //   33: ifeq -> 86
    //   36: aload_2
    //   37: invokeinterface next : ()Ljava/lang/Object;
    //   42: checkcast com/flurry/android/AdUnit
    //   45: astore_1
    //   46: aload_1
    //   47: invokevirtual b : ()Ljava/lang/Long;
    //   50: invokevirtual longValue : ()J
    //   53: invokestatic a : (J)Z
    //   56: ifeq -> 27
    //   59: aload_1
    //   60: invokevirtual c : ()Ljava/util/List;
    //   63: invokeinterface size : ()I
    //   68: ifle -> 27
    //   71: aload_2
    //   72: invokeinterface remove : ()V
    //   77: aload_0
    //   78: monitorexit
    //   79: aload_1
    //   80: areturn
    //   81: astore_1
    //   82: aload_0
    //   83: monitorexit
    //   84: aload_1
    //   85: athrow
    //   86: aconst_null
    //   87: astore_1
    //   88: goto -> 77
    // Exception table:
    //   from	to	target	type
    //   2	16	81	finally
    //   20	27	81	finally
    //   27	77	81	finally
  }
  
  final List a(String paramString, int paramInt) {
    // Byte code:
    //   0: aload_0
    //   1: monitorenter
    //   2: new java/util/ArrayList
    //   5: astore_3
    //   6: aload_3
    //   7: invokespecial <init> : ()V
    //   10: aload_0
    //   11: getfield a : Ljava/util/Map;
    //   14: aload_1
    //   15: invokeinterface get : (Ljava/lang/Object;)Ljava/lang/Object;
    //   20: checkcast java/util/List
    //   23: astore_1
    //   24: aload_1
    //   25: ifnull -> 127
    //   28: aload_1
    //   29: invokeinterface iterator : ()Ljava/util/Iterator;
    //   34: astore_1
    //   35: aload_1
    //   36: invokeinterface hasNext : ()Z
    //   41: ifeq -> 127
    //   44: aload_3
    //   45: invokeinterface size : ()I
    //   50: iload_2
    //   51: if_icmpgt -> 127
    //   54: aload_1
    //   55: invokeinterface next : ()Ljava/lang/Object;
    //   60: checkcast com/flurry/android/AdUnit
    //   63: astore #4
    //   65: aload #4
    //   67: invokevirtual b : ()Ljava/lang/Long;
    //   70: invokevirtual longValue : ()J
    //   73: invokestatic a : (J)Z
    //   76: ifeq -> 35
    //   79: aload #4
    //   81: invokevirtual d : ()Ljava/lang/Integer;
    //   84: invokevirtual intValue : ()I
    //   87: iconst_1
    //   88: if_icmpne -> 35
    //   91: aload #4
    //   93: invokevirtual c : ()Ljava/util/List;
    //   96: invokeinterface size : ()I
    //   101: ifle -> 35
    //   104: aload_3
    //   105: aload #4
    //   107: invokeinterface add : (Ljava/lang/Object;)Z
    //   112: pop
    //   113: aload_1
    //   114: invokeinterface remove : ()V
    //   119: goto -> 35
    //   122: astore_1
    //   123: aload_0
    //   124: monitorexit
    //   125: aload_1
    //   126: athrow
    //   127: aload_0
    //   128: monitorexit
    //   129: aload_3
    //   130: areturn
    // Exception table:
    //   from	to	target	type
    //   2	24	122	finally
    //   28	35	122	finally
    //   35	119	122	finally
  }
  
  final void a(List<AdUnit> paramList) {
    // Byte code:
    //   0: aload_0
    //   1: monitorenter
    //   2: aload_1
    //   3: invokeinterface iterator : ()Ljava/util/Iterator;
    //   8: astore_3
    //   9: aload_3
    //   10: invokeinterface hasNext : ()Z
    //   15: ifeq -> 98
    //   18: aload_3
    //   19: invokeinterface next : ()Ljava/lang/Object;
    //   24: checkcast com/flurry/android/AdUnit
    //   27: astore #5
    //   29: aload #5
    //   31: invokevirtual a : ()Ljava/lang/CharSequence;
    //   34: invokevirtual toString : ()Ljava/lang/String;
    //   37: astore #4
    //   39: aload_0
    //   40: getfield a : Ljava/util/Map;
    //   43: aload #4
    //   45: invokeinterface get : (Ljava/lang/Object;)Ljava/lang/Object;
    //   50: checkcast java/util/List
    //   53: astore_2
    //   54: aload_2
    //   55: astore_1
    //   56: aload_2
    //   57: ifnonnull -> 68
    //   60: new java/util/ArrayList
    //   63: astore_1
    //   64: aload_1
    //   65: invokespecial <init> : ()V
    //   68: aload_1
    //   69: aload #5
    //   71: invokeinterface add : (Ljava/lang/Object;)Z
    //   76: pop
    //   77: aload_0
    //   78: getfield a : Ljava/util/Map;
    //   81: aload #4
    //   83: aload_1
    //   84: invokeinterface put : (Ljava/lang/Object;Ljava/lang/Object;)Ljava/lang/Object;
    //   89: pop
    //   90: goto -> 9
    //   93: astore_1
    //   94: aload_0
    //   95: monitorexit
    //   96: aload_1
    //   97: athrow
    //   98: aload_0
    //   99: monitorexit
    //   100: return
    // Exception table:
    //   from	to	target	type
    //   2	9	93	finally
    //   9	54	93	finally
    //   60	68	93	finally
    //   68	90	93	finally
  }
  
  final boolean b(String paramString) {
    // Byte code:
    //   0: aload_0
    //   1: monitorenter
    //   2: aload_0
    //   3: getfield a : Ljava/util/Map;
    //   6: aload_1
    //   7: invokeinterface get : (Ljava/lang/Object;)Ljava/lang/Object;
    //   12: checkcast java/util/List
    //   15: astore_1
    //   16: aload_1
    //   17: ifnull -> 74
    //   20: aload_1
    //   21: invokeinterface isEmpty : ()Z
    //   26: ifne -> 74
    //   29: aload_1
    //   30: invokeinterface iterator : ()Ljava/util/Iterator;
    //   35: astore_1
    //   36: aload_1
    //   37: invokeinterface hasNext : ()Z
    //   42: ifeq -> 74
    //   45: aload_1
    //   46: invokeinterface next : ()Ljava/lang/Object;
    //   51: checkcast com/flurry/android/AdUnit
    //   54: invokevirtual b : ()Ljava/lang/Long;
    //   57: invokevirtual longValue : ()J
    //   60: invokestatic a : (J)Z
    //   63: istore_2
    //   64: iload_2
    //   65: ifeq -> 36
    //   68: iconst_1
    //   69: istore_2
    //   70: aload_0
    //   71: monitorexit
    //   72: iload_2
    //   73: ireturn
    //   74: iconst_0
    //   75: istore_2
    //   76: goto -> 70
    //   79: astore_1
    //   80: aload_0
    //   81: monitorexit
    //   82: aload_1
    //   83: athrow
    // Exception table:
    //   from	to	target	type
    //   2	16	79	finally
    //   20	36	79	finally
    //   36	64	79	finally
  }
}


/* Location:              C:\Users\walle\Downloads\boomlings-1-20 (2)\classes-dex2jar.jar!\com\flurry\android\aa.class
 * Java compiler version: 6 (50.0)
 * JD-Core Version:       1.1.3
 */