package com.flurry.android;

final class bc extends an {
  private String a;
  
  private InstallReceiver b;
  
  bc(InstallReceiver paramInstallReceiver, String paramString) {}
  
  public final void a() {
    // Byte code:
    //   0: aconst_null
    //   1: astore_2
    //   2: aconst_null
    //   3: astore #4
    //   5: aload_2
    //   6: astore_1
    //   7: aload_0
    //   8: getfield b : Lcom/flurry/android/InstallReceiver;
    //   11: invokestatic a : (Lcom/flurry/android/InstallReceiver;)Ljava/io/File;
    //   14: invokevirtual getParentFile : ()Ljava/io/File;
    //   17: astore_3
    //   18: aload_2
    //   19: astore_1
    //   20: new java/lang/StringBuilder
    //   23: astore #5
    //   25: aload_2
    //   26: astore_1
    //   27: aload #5
    //   29: invokespecial <init> : ()V
    //   32: aload_2
    //   33: astore_1
    //   34: aload #5
    //   36: ldc 'dir is...'
    //   38: invokevirtual append : (Ljava/lang/String;)Ljava/lang/StringBuilder;
    //   41: aload_3
    //   42: invokevirtual toString : ()Ljava/lang/String;
    //   45: invokevirtual append : (Ljava/lang/String;)Ljava/lang/StringBuilder;
    //   48: invokevirtual toString : ()Ljava/lang/String;
    //   51: pop
    //   52: aload_2
    //   53: astore_1
    //   54: aload_3
    //   55: invokevirtual mkdirs : ()Z
    //   58: ifne -> 111
    //   61: aload_2
    //   62: astore_1
    //   63: aload_3
    //   64: invokevirtual exists : ()Z
    //   67: ifne -> 111
    //   70: aload_2
    //   71: astore_1
    //   72: new java/lang/StringBuilder
    //   75: astore #5
    //   77: aload_2
    //   78: astore_1
    //   79: aload #5
    //   81: invokespecial <init> : ()V
    //   84: aload_2
    //   85: astore_1
    //   86: ldc 'InstallReceiver'
    //   88: aload #5
    //   90: ldc 'Unable to create persistent dir: '
    //   92: invokevirtual append : (Ljava/lang/String;)Ljava/lang/StringBuilder;
    //   95: aload_3
    //   96: invokevirtual append : (Ljava/lang/Object;)Ljava/lang/StringBuilder;
    //   99: invokevirtual toString : ()Ljava/lang/String;
    //   102: invokestatic b : (Ljava/lang/String;Ljava/lang/String;)I
    //   105: pop
    //   106: aconst_null
    //   107: invokestatic a : (Ljava/io/Closeable;)V
    //   110: return
    //   111: aload_2
    //   112: astore_1
    //   113: new java/io/FileOutputStream
    //   116: dup
    //   117: aload_0
    //   118: getfield b : Lcom/flurry/android/InstallReceiver;
    //   121: invokestatic a : (Lcom/flurry/android/InstallReceiver;)Ljava/io/File;
    //   124: invokespecial <init> : (Ljava/io/File;)V
    //   127: astore_2
    //   128: aload_2
    //   129: aload_0
    //   130: getfield a : Ljava/lang/String;
    //   133: invokevirtual getBytes : ()[B
    //   136: invokevirtual write : ([B)V
    //   139: aload_0
    //   140: getfield b : Lcom/flurry/android/InstallReceiver;
    //   143: invokestatic a : (Lcom/flurry/android/InstallReceiver;)Ljava/io/File;
    //   146: invokestatic a : (Ljava/io/File;)Ljava/lang/String;
    //   149: invokestatic a : (Ljava/lang/String;)Ljava/util/Map;
    //   152: invokeinterface entrySet : ()Ljava/util/Set;
    //   157: invokeinterface iterator : ()Ljava/util/Iterator;
    //   162: astore_3
    //   163: aload_3
    //   164: invokeinterface hasNext : ()Z
    //   169: ifeq -> 253
    //   172: aload_3
    //   173: invokeinterface next : ()Ljava/lang/Object;
    //   178: checkcast java/util/Map$Entry
    //   181: astore #4
    //   183: new java/lang/StringBuilder
    //   186: astore_1
    //   187: aload_1
    //   188: invokespecial <init> : ()V
    //   191: aload_1
    //   192: ldc 'entry: '
    //   194: invokevirtual append : (Ljava/lang/String;)Ljava/lang/StringBuilder;
    //   197: aload #4
    //   199: invokeinterface getKey : ()Ljava/lang/Object;
    //   204: checkcast java/lang/String
    //   207: invokevirtual append : (Ljava/lang/String;)Ljava/lang/StringBuilder;
    //   210: ldc '='
    //   212: invokevirtual append : (Ljava/lang/String;)Ljava/lang/StringBuilder;
    //   215: aload #4
    //   217: invokeinterface getValue : ()Ljava/lang/Object;
    //   222: invokevirtual append : (Ljava/lang/Object;)Ljava/lang/StringBuilder;
    //   225: invokevirtual toString : ()Ljava/lang/String;
    //   228: pop
    //   229: goto -> 163
    //   232: astore_1
    //   233: aload_1
    //   234: astore_3
    //   235: aload_2
    //   236: astore_1
    //   237: ldc 'InstallReceiver'
    //   239: ldc ''
    //   241: aload_3
    //   242: invokestatic b : (Ljava/lang/String;Ljava/lang/String;Ljava/lang/Throwable;)I
    //   245: pop
    //   246: aload_2
    //   247: invokestatic a : (Ljava/io/Closeable;)V
    //   250: goto -> 110
    //   253: aload_2
    //   254: invokestatic a : (Ljava/io/Closeable;)V
    //   257: goto -> 110
    //   260: astore_2
    //   261: aload_1
    //   262: invokestatic a : (Ljava/io/Closeable;)V
    //   265: aload_2
    //   266: athrow
    //   267: astore_1
    //   268: aload_2
    //   269: astore_3
    //   270: aload_1
    //   271: astore_2
    //   272: aload_3
    //   273: astore_1
    //   274: goto -> 261
    //   277: astore_3
    //   278: aload #4
    //   280: astore_2
    //   281: goto -> 235
    // Exception table:
    //   from	to	target	type
    //   7	18	277	java/lang/Throwable
    //   7	18	260	finally
    //   20	25	277	java/lang/Throwable
    //   20	25	260	finally
    //   27	32	277	java/lang/Throwable
    //   27	32	260	finally
    //   34	52	277	java/lang/Throwable
    //   34	52	260	finally
    //   54	61	277	java/lang/Throwable
    //   54	61	260	finally
    //   63	70	277	java/lang/Throwable
    //   63	70	260	finally
    //   72	77	277	java/lang/Throwable
    //   72	77	260	finally
    //   79	84	277	java/lang/Throwable
    //   79	84	260	finally
    //   86	106	277	java/lang/Throwable
    //   86	106	260	finally
    //   113	128	277	java/lang/Throwable
    //   113	128	260	finally
    //   128	163	232	java/lang/Throwable
    //   128	163	267	finally
    //   163	229	232	java/lang/Throwable
    //   163	229	267	finally
    //   237	246	260	finally
  }
}


/* Location:              C:\Users\walle\Downloads\boomlings-1-20 (2)\classes-dex2jar.jar!\com\flurry\android\bc.class
 * Java compiler version: 6 (50.0)
 * JD-Core Version:       1.1.3
 */