package com.flurry.android;

import android.content.Context;
import android.view.ViewGroup;
import java.util.HashMap;
import java.util.Map;

final class bn {
  private static String a = "FlurryAgent";
  
  private static Runnable f;
  
  private Map b = new HashMap<Object, Object>();
  
  private Map c = new HashMap<Object, Object>();
  
  private Map d = new HashMap<Object, Object>();
  
  private Context e;
  
  bn(Context paramContext) {
    this.e = paramContext;
  }
  
  final x a(bo parambo, Context paramContext, ViewGroup paramViewGroup, String paramString) {
    // Byte code:
    //   0: aload_0
    //   1: monitorenter
    //   2: aload_0
    //   3: getfield c : Ljava/util/Map;
    //   6: aload #4
    //   8: invokeinterface get : (Ljava/lang/Object;)Ljava/lang/Object;
    //   13: checkcast java/lang/ref/WeakReference
    //   16: astore #5
    //   18: aload #5
    //   20: ifnonnull -> 68
    //   23: new com/flurry/android/x
    //   26: astore #5
    //   28: aload #5
    //   30: aload_1
    //   31: aload_2
    //   32: aload #4
    //   34: aload_3
    //   35: invokespecial <init> : (Lcom/flurry/android/bo;Landroid/content/Context;Ljava/lang/String;Landroid/view/ViewGroup;)V
    //   38: new java/lang/ref/WeakReference
    //   41: astore_1
    //   42: aload_1
    //   43: aload #5
    //   45: invokespecial <init> : (Ljava/lang/Object;)V
    //   48: aload_0
    //   49: getfield c : Ljava/util/Map;
    //   52: aload #4
    //   54: aload_1
    //   55: invokeinterface put : (Ljava/lang/Object;Ljava/lang/Object;)Ljava/lang/Object;
    //   60: pop
    //   61: aload #5
    //   63: astore_1
    //   64: aload_0
    //   65: monitorexit
    //   66: aload_1
    //   67: areturn
    //   68: aload #5
    //   70: invokevirtual get : ()Ljava/lang/Object;
    //   73: checkcast com/flurry/android/x
    //   76: astore_1
    //   77: goto -> 64
    //   80: astore_1
    //   81: aload_0
    //   82: monitorexit
    //   83: aload_1
    //   84: athrow
    // Exception table:
    //   from	to	target	type
    //   2	18	80	finally
    //   23	61	80	finally
    //   68	77	80	finally
  }
  
  final x a(String paramString) {
    // Byte code:
    //   0: aload_0
    //   1: monitorenter
    //   2: aload_0
    //   3: getfield c : Ljava/util/Map;
    //   6: aload_1
    //   7: invokeinterface containsKey : (Ljava/lang/Object;)Z
    //   12: ifeq -> 39
    //   15: aload_0
    //   16: getfield c : Ljava/util/Map;
    //   19: aload_1
    //   20: invokeinterface get : (Ljava/lang/Object;)Ljava/lang/Object;
    //   25: checkcast java/lang/ref/WeakReference
    //   28: invokevirtual get : ()Ljava/lang/Object;
    //   31: checkcast com/flurry/android/x
    //   34: astore_1
    //   35: aload_0
    //   36: monitorexit
    //   37: aload_1
    //   38: areturn
    //   39: aconst_null
    //   40: astore_1
    //   41: goto -> 35
    //   44: astore_1
    //   45: aload_0
    //   46: monitorexit
    //   47: aload_1
    //   48: athrow
    // Exception table:
    //   from	to	target	type
    //   2	35	44	finally
  }
  
  final void a() {
    // Byte code:
    //   0: aload_0
    //   1: monitorenter
    //   2: aload_0
    //   3: getfield d : Ljava/util/Map;
    //   6: aload_0
    //   7: getfield e : Landroid/content/Context;
    //   10: invokeinterface get : (Ljava/lang/Object;)Ljava/lang/Object;
    //   15: checkcast java/util/List
    //   18: astore_1
    //   19: aload_1
    //   20: ifnull -> 76
    //   23: aload_1
    //   24: invokeinterface iterator : ()Ljava/util/Iterator;
    //   29: astore_2
    //   30: aload_2
    //   31: invokeinterface hasNext : ()Z
    //   36: ifeq -> 76
    //   39: aload_2
    //   40: invokeinterface next : ()Ljava/lang/Object;
    //   45: checkcast com/flurry/android/x
    //   48: astore_1
    //   49: aload_1
    //   50: invokevirtual a : ()I
    //   53: ifle -> 30
    //   56: aload_1
    //   57: invokevirtual b : ()Z
    //   60: ifne -> 30
    //   63: aload_0
    //   64: aload_1
    //   65: invokevirtual a : (Lcom/flurry/android/x;)V
    //   68: goto -> 30
    //   71: astore_1
    //   72: aload_0
    //   73: monitorexit
    //   74: aload_1
    //   75: athrow
    //   76: aload_0
    //   77: monitorexit
    //   78: return
    // Exception table:
    //   from	to	target	type
    //   2	19	71	finally
    //   23	30	71	finally
    //   30	68	71	finally
  }
  
  final void a(Context paramContext) {
    // Byte code:
    //   0: aload_0
    //   1: monitorenter
    //   2: aload_0
    //   3: aload_1
    //   4: putfield e : Landroid/content/Context;
    //   7: aload_0
    //   8: monitorexit
    //   9: return
    //   10: astore_1
    //   11: aload_0
    //   12: monitorexit
    //   13: aload_1
    //   14: athrow
    // Exception table:
    //   from	to	target	type
    //   2	7	10	finally
  }
  
  final void a(x paramx) {
    // Byte code:
    //   0: aload_0
    //   1: monitorenter
    //   2: new com/flurry/android/as
    //   5: astore_2
    //   6: aload_2
    //   7: aload_0
    //   8: aload_1
    //   9: invokespecial <init> : (Lcom/flurry/android/bn;Lcom/flurry/android/x;)V
    //   12: aload_2
    //   13: putstatic com/flurry/android/bn.f : Ljava/lang/Runnable;
    //   16: aload_1
    //   17: invokevirtual b : ()Z
    //   20: ifne -> 41
    //   23: aload_1
    //   24: getstatic com/flurry/android/bn.f : Ljava/lang/Runnable;
    //   27: aload_1
    //   28: invokevirtual a : ()I
    //   31: i2l
    //   32: invokevirtual postDelayed : (Ljava/lang/Runnable;J)Z
    //   35: pop
    //   36: aload_1
    //   37: iconst_1
    //   38: invokevirtual a : (Z)V
    //   41: aload_0
    //   42: monitorexit
    //   43: return
    //   44: astore_1
    //   45: aload_0
    //   46: monitorexit
    //   47: aload_1
    //   48: athrow
    // Exception table:
    //   from	to	target	type
    //   2	41	44	finally
  }
  
  final void a(String paramString, aj paramaj) {
    // Byte code:
    //   0: aload_0
    //   1: monitorenter
    //   2: aload_0
    //   3: getfield b : Ljava/util/Map;
    //   6: aload_1
    //   7: aload_2
    //   8: invokeinterface put : (Ljava/lang/Object;Ljava/lang/Object;)Ljava/lang/Object;
    //   13: pop
    //   14: aload_0
    //   15: monitorexit
    //   16: return
    //   17: astore_1
    //   18: aload_0
    //   19: monitorexit
    //   20: aload_1
    //   21: athrow
    // Exception table:
    //   from	to	target	type
    //   2	14	17	finally
  }
  
  final void b(x paramx) {
    // Byte code:
    //   0: aload_0
    //   1: monitorenter
    //   2: aload_1
    //   3: iconst_0
    //   4: invokevirtual a : (Z)V
    //   7: new java/lang/StringBuilder
    //   10: astore_2
    //   11: aload_2
    //   12: invokespecial <init> : ()V
    //   15: aload_2
    //   16: ldc 'Rotating banner for adSpace: '
    //   18: invokevirtual append : (Ljava/lang/String;)Ljava/lang/StringBuilder;
    //   21: aload_1
    //   22: invokevirtual d : ()Ljava/lang/String;
    //   25: invokevirtual append : (Ljava/lang/String;)Ljava/lang/StringBuilder;
    //   28: invokevirtual toString : ()Ljava/lang/String;
    //   31: pop
    //   32: aload_1
    //   33: invokevirtual f : ()V
    //   36: aload_1
    //   37: invokevirtual a : ()I
    //   40: ifle -> 48
    //   43: aload_0
    //   44: aload_1
    //   45: invokevirtual a : (Lcom/flurry/android/x;)V
    //   48: aload_0
    //   49: monitorexit
    //   50: return
    //   51: astore_1
    //   52: aload_0
    //   53: monitorexit
    //   54: aload_1
    //   55: athrow
    // Exception table:
    //   from	to	target	type
    //   2	48	51	finally
  }
  
  final void b(String paramString) {
    // Byte code:
    //   0: aload_0
    //   1: monitorenter
    //   2: aload_0
    //   3: getfield c : Ljava/util/Map;
    //   6: aload_1
    //   7: invokeinterface remove : (Ljava/lang/Object;)Ljava/lang/Object;
    //   12: pop
    //   13: aload_0
    //   14: monitorexit
    //   15: return
    //   16: astore_1
    //   17: aload_0
    //   18: monitorexit
    //   19: aload_1
    //   20: athrow
    // Exception table:
    //   from	to	target	type
    //   2	13	16	finally
  }
  
  final aj c(String paramString) {
    // Byte code:
    //   0: aload_0
    //   1: monitorenter
    //   2: aload_0
    //   3: getfield b : Ljava/util/Map;
    //   6: aload_1
    //   7: invokeinterface get : (Ljava/lang/Object;)Ljava/lang/Object;
    //   12: checkcast com/flurry/android/aj
    //   15: astore_2
    //   16: aload_2
    //   17: astore_1
    //   18: aload_2
    //   19: ifnonnull -> 30
    //   22: new com/flurry/android/ba
    //   25: dup
    //   26: invokespecial <init> : ()V
    //   29: astore_1
    //   30: aload_0
    //   31: monitorexit
    //   32: aload_1
    //   33: areturn
    //   34: astore_1
    //   35: aload_0
    //   36: monitorexit
    //   37: aload_1
    //   38: athrow
    // Exception table:
    //   from	to	target	type
    //   2	16	34	finally
    //   22	30	34	finally
  }
  
  final void d(String paramString) {
    // Byte code:
    //   0: aload_0
    //   1: monitorenter
    //   2: aload_0
    //   3: getfield b : Ljava/util/Map;
    //   6: aload_1
    //   7: invokeinterface containsKey : (Ljava/lang/Object;)Z
    //   12: ifeq -> 26
    //   15: aload_0
    //   16: getfield b : Ljava/util/Map;
    //   19: aload_1
    //   20: invokeinterface remove : (Ljava/lang/Object;)Ljava/lang/Object;
    //   25: pop
    //   26: aload_0
    //   27: monitorexit
    //   28: return
    //   29: astore_1
    //   30: aload_0
    //   31: monitorexit
    //   32: aload_1
    //   33: athrow
    // Exception table:
    //   from	to	target	type
    //   2	26	29	finally
  }
}


/* Location:              C:\Users\walle\Downloads\boomlings-1-20 (2)\classes-dex2jar.jar!\com\flurry\android\bn.class
 * Java compiler version: 6 (50.0)
 * JD-Core Version:       1.1.3
 */